sql/__init__.py
postgresql_orm-0.5.8.dist-info/METADATA
postgresql_orm-0.5.8.dist-info/WHEEL
postgresql_orm-0.5.8.dist-info/top_level.txt
postgresql_orm-0.5.8.dist-info/RECORD
