Metadata-Version: 2.1
Name: postgresql-orm
Version: 0.5.8
Summary: Easyest PostgreSQL ORM
Home-page: https://github.com/hazardland/sql.py
Author: Vakhtang Zardiashvili
Author-email: hazardland@gmail.com
License: MIT
Keywords: orm,pgsql,postgresql,model
Platform: UNKNOWN
Requires-Python: >=3.6
Requires-Dist: python-dateutil
